[
 {
   "id": 1,
   "lat": 60.15544479,
   "lng": 24.95029289,
   "name": "Kaivopuisto",
   "total": 7576,
   "origin": 3735,
   "originPercent": 0.493004224,
   "destination": 3841,
   "destinationPercent": 0.506995776
 },
 {
   "id": 2,
   "lat": 60.16095909,
   "lng": 24.95634747,
   "name": "Laivasillankatu",
   "total": 4539,
   "origin": 2258,
   "originPercent": 0.497466402,
   "destination": 2281,
   "destinationPercent": 0.502533598
 },
 {
   "id": 3,
   "lat": 60.1581892,
   "lng": 24.9449274,
   "name": "Kapteeninpuistikko",
   "total": 6611,
   "origin": 3375,
   "originPercent": 0.510512782,
   "destination": 3236,
   "destinationPercent": 0.489487218
 },
 {
   "id": 4,
   "lat": 60.1609859,
   "lng": 24.9417758,
   "name": "Viiskulma",
   "total": 7114,
   "origin": 3561,
   "originPercent": 0.500562272,
   "destination": 3553,
   "destinationPercent": 0.499437728
 },
 {
   "id": 5,
   "lat": 60.1579483,
   "lng": 24.9362853,
   "name": "Sepänkatu",
   "total": 9194,
   "origin": 4648,
   "originPercent": 0.505547096,
   "destination": 4546,
   "destinationPercent": 0.494452904
 },
 {
   "id": 6,
   "lat": 60.1622251,
   "lng": 24.9297099,
   "name": "Hietalahdentori",
   "total": 12777,
   "origin": 6395,
   "originPercent": 0.500508727,
   "destination": 6382,
   "destinationPercent": 0.499491273
 },
 {
   "id": 7,
   "lat": 60.1631032,
   "lng": 24.94596,
   "name": "Designmuseo",
   "total": 4719,
   "origin": 2407,
   "originPercent": 0.510065692,
   "destination": 2312,
   "destinationPercent": 0.489934308
 },
 {
   "id": 8,
   "lat": 60.1652883,
   "lng": 24.9391499,
   "name": "Vanha kirkkopuisto",
   "total": 10265,
   "origin": 5140,
   "originPercent": 0.500730638,
   "destination": 5125,
   "destinationPercent": 0.499269362
 },
 {
   "id": 9,
   "lat": 60.16691167,
   "lng": 24.94413493,
   "name": "Erottajan aukio",
   "total": 0,
   "origin": 0,
   "originPercent": 0,
   "destination": 0,
   "destinationPercent": 0
 },
 {
   "id": 10,
   "lat": 60.16501718,
   "lng": 24.94947288,
   "name": "Kasarmitori",
   "total": 5090,
   "origin": 2558,
   "originPercent": 0.502554028,
   "destination": 2532,
   "destinationPercent": 0.497445972
 },
 {
   "id": 11,
   "lat": 60.1674573,
   "lng": 24.9510227,
   "name": "Unioninkatu",
   "total": 10545,
   "origin": 4728,
   "originPercent": 0.448364154,
   "destination": 5817,
   "destinationPercent": 0.551635846
 },
 {
   "id": 12,
   "lat": 60.168384,
   "lng": 24.9583814,
   "name": "Kanavaranta",
   "total": 13550,
   "origin": 6675,
   "originPercent": 0.492619926,
   "destination": 6875,
   "destinationPercent": 0.507380074
 },
 {
   "id": 13,
   "lat": 60.1678703,
   "lng": 24.9755341,
   "name": "Merisotilaantori",
   "total": 2992,
   "origin": 1437,
   "originPercent": 0.480280749,
   "destination": 1555,
   "destinationPercent": 0.519719251
 },
 {
   "id": 14,
   "lat": 60.1691278,
   "lng": 24.9526414,
   "name": "Senaatintori",
   "total": 5217,
   "origin": 2559,
   "originPercent": 0.490511788,
   "destination": 2658,
   "destinationPercent": 0.509488212
 },
 {
   "id": 15,
   "lat": 60.17110665,
   "lng": 24.95555819,
   "name": "Ritarikatu",
   "total": 4932,
   "origin": 2440,
   "originPercent": 0.494728305,
   "destination": 2492,
   "destinationPercent": 0.505271695
 },
 {
   "id": 16,
   "lat": 60.1741822,
   "lng": 24.9613747,
   "name": "Liisanpuistikko",
   "total": 9071,
   "origin": 4486,
   "originPercent": 0.494543049,
   "destination": 4585,
   "destinationPercent": 0.505456951
 },
 {
   "id": 17,
   "lat": 60.1731029,
   "lng": 24.9494791,
   "name": "Varsapuistikko",
   "total": 9228,
   "origin": 4598,
   "originPercent": 0.498266147,
   "destination": 4630,
   "destinationPercent": 0.501733853
 },
 {
   "id": 18,
   "lat": 60.16986223,
   "lng": 24.9481464,
   "name": "Porthania",
   "total": 14383,
   "origin": 7200,
   "originPercent": 0.500590975,
   "destination": 7183,
   "destinationPercent": 0.499409025
 },
 {
   "id": 19,
   "lat": 60.1708236,
   "lng": 24.9425268,
   "name": "Rautatientori / itä",
   "total": 15782,
   "origin": 7867,
   "originPercent": 0.49847928,
   "destination": 7915,
   "destinationPercent": 0.50152072
 },
 {
   "id": 20,
   "lat": 60.17319894,
   "lng": 24.943301,
   "name": "Kaisaniemenpuisto",
   "total": 9735,
   "origin": 4893,
   "originPercent": 0.502619414,
   "destination": 4842,
   "destinationPercent": 0.497380586
 },
 {
   "id": 21,
   "lat": 60.1729435,
   "lng": 24.939284,
   "name": "Töölönlahdenkatu",
   "total": 30875,
   "origin": 15453,
   "originPercent": 0.500502024,
   "destination": 15422,
   "destinationPercent": 0.499497976
 },
 {
   "id": 22,
   "lat": 60.1706061,
   "lng": 24.9397601,
   "name": "Rautatientori / länsi",
   "total": 16977,
   "origin": 8500,
   "originPercent": 0.500677387,
   "destination": 8477,
   "destinationPercent": 0.499322613
 },
 {
   "id": 23,
   "lat": 60.1712579,
   "lng": 24.9374279,
   "name": "Kiasma",
   "total": 9300,
   "origin": 4655,
   "originPercent": 0.500537634,
   "destination": 4645,
   "destinationPercent": 0.499462366
 },
 {
   "id": 24,
   "lat": 60.1690724,
   "lng": 24.9394195,
   "name": "Mannerheimintie",
   "total": 11401,
   "origin": 5710,
   "originPercent": 0.50083326,
   "destination": 5691,
   "destinationPercent": 0.49916674
 },
 {
   "id": 25,
   "lat": 60.1700844,
   "lng": 24.9351212,
   "name": "Narinkka",
   "total": 11663,
   "origin": 5880,
   "originPercent": 0.50415845,
   "destination": 5783,
   "destinationPercent": 0.49584155
 },
 {
   "id": 26,
   "lat": 60.1686095,
   "lng": 24.9305373,
   "name": "Kampin metroasema",
   "total": 18122,
   "origin": 9242,
   "originPercent": 0.50998786,
   "destination": 8880,
   "destinationPercent": 0.49001214
 },
 {
   "id": 27,
   "lat": 60.1673332,
   "lng": 24.9357851,
   "name": "Eerikinkatu",
   "total": 3921,
   "origin": 1986,
   "originPercent": 0.506503443,
   "destination": 1935,
   "destinationPercent": 0.493496557
 },
 {
   "id": 28,
   "lat": 60.1658121,
   "lng": 24.927021,
   "name": "Lastenlehto",
   "total": 4121,
   "origin": 2112,
   "originPercent": 0.512496967,
   "destination": 2009,
   "destinationPercent": 0.487503033
 },
 {
   "id": 29,
   "lat": 60.164088,
   "lng": 24.9225658,
   "name": "Baana",
   "total": 10131,
   "origin": 5037,
   "originPercent": 0.497186852,
   "destination": 5094,
   "destinationPercent": 0.502813148
 },
 {
   "id": 30,
   "lat": 60.1635309,
   "lng": 24.9145165,
   "name": "Itämerentori",
   "total": 25162,
   "origin": 12546,
   "originPercent": 0.498609014,
   "destination": 12616,
   "destinationPercent": 0.501390986
 },
 {
   "id": 31,
   "lat": 60.1680998,
   "lng": 24.9220763,
   "name": "Marian Sairaala",
   "total": 8229,
   "origin": 4126,
   "originPercent": 0.501397497,
   "destination": 4103,
   "destinationPercent": 0.498602503
 },
 {
   "id": 32,
   "lat": 60.17187006,
   "lng": 24.93122341,
   "name": "Eläinmuseo",
   "total": 2602,
   "origin": 1396,
   "originPercent": 0.536510377,
   "destination": 1206,
   "destinationPercent": 0.463489623
 },
 {
   "id": 33,
   "lat": 60.1711591,
   "lng": 24.924961,
   "name": "Kauppakorkeakoulu",
   "total": 6779,
   "origin": 3387,
   "originPercent": 0.499631214,
   "destination": 3392,
   "destinationPercent": 0.500368786
 },
 {
   "id": 34,
   "lat": 60.1739641,
   "lng": 24.9329875,
   "name": "Kansallismuseo",
   "total": 4720,
   "origin": 2391,
   "originPercent": 0.506567797,
   "destination": 2329,
   "destinationPercent": 0.493432203
 },
 {
   "id": 35,
   "lat": 60.17406372,
   "lng": 24.92822758,
   "name": "Cygnauksenkatu",
   "total": 3854,
   "origin": 1989,
   "originPercent": 0.516087182,
   "destination": 1865,
   "destinationPercent": 0.483912818
 },
 {
   "id": 36,
   "lat": 60.1760798,
   "lng": 24.9223942,
   "name": "Apollonkatu",
   "total": 10440,
   "origin": 5187,
   "originPercent": 0.49683908,
   "destination": 5253,
   "destinationPercent": 0.50316092
 },
 {
   "id": 37,
   "lat": 60.1775598,
   "lng": 24.9283272,
   "name": "Töölönkatu",
   "total": 8508,
   "origin": 4259,
   "originPercent": 0.500587682,
   "destination": 4249,
   "destinationPercent": 0.499412318
 },
 {
   "id": 38,
   "lat": 60.1791231,
   "lng": 24.9249114,
   "name": "Töölöntori",
   "total": 5778,
   "origin": 2931,
   "originPercent": 0.507268951,
   "destination": 2847,
   "destinationPercent": 0.492731049
 },
 {
   "id": 39,
   "lat": 60.1825529,
   "lng": 24.926687,
   "name": "Ooppera",
   "total": 12499,
   "origin": 6221,
   "originPercent": 0.497719818,
   "destination": 6278,
   "destinationPercent": 0.502280182
 },
 {
   "id": 40,
   "lat": 60.17810632,
   "lng": 24.95218125,
   "name": "Hakaniemen metroasema",
   "total": 10583,
   "origin": 5351,
   "originPercent": 0.505622224,
   "destination": 5232,
   "destinationPercent": 0.494377776
 },
 {
   "id": 41,
   "lat": 60.180863,
   "lng": 24.9494,
   "name": "Ympyrätalo",
   "total": 17389,
   "origin": 8622,
   "originPercent": 0.495830698,
   "destination": 8767,
   "destinationPercent": 0.504169302
 },
 {
   "id": 42,
   "lat": 60.18310658,
   "lng": 24.95518082,
   "name": "Haapaniemenkatu",
   "total": 3310,
   "origin": 1713,
   "originPercent": 0.517522659,
   "destination": 1597,
   "destinationPercent": 0.482477341
 },
 {
   "id": 43,
   "lat": 60.1842833,
   "lng": 24.9526763,
   "name": "Karhupuisto",
   "total": 4965,
   "origin": 2636,
   "originPercent": 0.530916415,
   "destination": 2329,
   "destinationPercent": 0.469083585
 },
 {
   "id": 44,
   "lat": 60.18803805,
   "lng": 24.96089211,
   "name": "Sörnäisten metroasema",
   "total": 12536,
   "origin": 6337,
   "originPercent": 0.505504148,
   "destination": 6199,
   "destinationPercent": 0.494495852
 },
 {
   "id": 45,
   "lat": 60.1868618,
   "lng": 24.9509168,
   "name": "Brahen kenttä",
   "total": 7896,
   "origin": 4069,
   "originPercent": 0.515324215,
   "destination": 3827,
   "destinationPercent": 0.484675785
 },
 {
   "id": 46,
   "lat": 60.1862877,
   "lng": 24.9418576,
   "name": "Diakoniapuisto",
   "total": 6427,
   "origin": 3231,
   "originPercent": 0.502722888,
   "destination": 3196,
   "destinationPercent": 0.497277112
 },
 {
   "id": 47,
   "lat": 60.16673072,
   "lng": 24.95350467,
   "name": "Vanha Kauppahalli",
   "total": 2708,
   "origin": 1354,
   "originPercent": 0.5,
   "destination": 1354,
   "destinationPercent": 0.5
 },
 {
   "id": 48,
   "lat": 60.1647545,
   "lng": 24.9674861,
   "name": "Mastokatu",
   "total": 3513,
   "origin": 1703,
   "originPercent": 0.484770851,
   "destination": 1810,
   "destinationPercent": 0.515229149
 },
 {
   "id": 49,
   "lat": 60.16345894,
   "lng": 24.94177084,
   "name": "Annankatu",
   "total": 7813,
   "origin": 3907,
   "originPercent": 0.500063996,
   "destination": 3906,
   "destinationPercent": 0.499936004
 },
 {
   "id": 50,
   "lat": 60.1498127,
   "lng": 24.8861094,
   "name": "Melkonkuja",
   "total": 2968,
   "origin": 1467,
   "originPercent": 0.494272237,
   "destination": 1501,
   "destinationPercent": 0.505727763
 },
 {
   "id": 51,
   "lat": 60.15066,
   "lng": 24.8812502,
   "name": "Itälahdenkatu",
   "total": 4778,
   "origin": 2395,
   "originPercent": 0.501255756,
   "destination": 2383,
   "destinationPercent": 0.498744244
 },
 {
   "id": 52,
   "lat": 60.1540763,
   "lng": 24.8793159,
   "name": "Heikkilänaukio",
   "total": 5100,
   "origin": 2556,
   "originPercent": 0.501176471,
   "destination": 2544,
   "destinationPercent": 0.498823529
 },
 {
   "id": 53,
   "lat": 60.156817,
   "lng": 24.8850653,
   "name": "Heikkiläntie",
   "total": 5192,
   "origin": 2571,
   "originPercent": 0.4951849,
   "destination": 2621,
   "destinationPercent": 0.5048151
 },
 {
   "id": 54,
   "lat": 60.1583842,
   "lng": 24.8766658,
   "name": "Gyldenintie",
   "total": 9876,
   "origin": 4938,
   "originPercent": 0.5,
   "destination": 4938,
   "destinationPercent": 0.5
 },
 {
   "id": 55,
   "lat": 60.16169596,
   "lng": 24.85986627,
   "name": "Puistokaari",
   "total": 1788,
   "origin": 923,
   "originPercent": 0.516219239,
   "destination": 865,
   "destinationPercent": 0.483780761
 },
 {
   "id": 56,
   "lat": 60.1654485,
   "lng": 24.8601992,
   "name": "Luoteisväylä",
   "total": 2766,
   "origin": 1314,
   "originPercent": 0.47505423,
   "destination": 1452,
   "destinationPercent": 0.52494577
 },
 {
   "id": 57,
   "lat": 60.1603306,
   "lng": 24.8815441,
   "name": "Lauttasaaren ostoskeskus",
   "total": 6620,
   "origin": 3296,
   "originPercent": 0.497885196,
   "destination": 3324,
   "destinationPercent": 0.502114804
 },
 {
   "id": 58,
   "lat": 60.1615512,
   "lng": 24.8926386,
   "name": "Lauttasaarensilta",
   "total": 6046,
   "origin": 3026,
   "originPercent": 0.500496196,
   "destination": 3020,
   "destinationPercent": 0.499503804
 },
 {
   "id": 59,
   "lat": 60.16478138,
   "lng": 24.9009608,
   "name": "Salmisaarenranta",
   "total": 8069,
   "origin": 3816,
   "originPercent": 0.472921056,
   "destination": 4253,
   "destinationPercent": 0.527078944
 },
 {
   "id": 60,
   "lat": 60.1632493,
   "lng": 24.905336,
   "name": "Porkkalankatu",
   "total": 8472,
   "origin": 4243,
   "originPercent": 0.500826251,
   "destination": 4229,
   "destinationPercent": 0.499173749
 },
 {
   "id": 61,
   "lat": 60.1589276,
   "lng": 24.909692,
   "name": "Länsisatamankatu",
   "total": 3690,
   "origin": 1825,
   "originPercent": 0.494579946,
   "destination": 1865,
   "destinationPercent": 0.505420054
 },
 {
   "id": 62,
   "lat": 60.1610901,
   "lng": 24.9158734,
   "name": "Messitytönkatu",
   "total": 5121,
   "origin": 2558,
   "originPercent": 0.499511814,
   "destination": 2563,
   "destinationPercent": 0.500488186
 },
 {
   "id": 63,
   "lat": 60.1619311,
   "lng": 24.9214896,
   "name": "Jätkäsaarenlaituri",
   "total": 9726,
   "origin": 4849,
   "originPercent": 0.498560559,
   "destination": 4877,
   "destinationPercent": 0.501439441
 },
 {
   "id": 64,
   "lat": 60.1565255,
   "lng": 24.9217464,
   "name": "Tyynenmerenkatu",
   "total": 9827,
   "origin": 4905,
   "originPercent": 0.499135036,
   "destination": 4922,
   "destinationPercent": 0.500864964
 },
 {
   "id": 65,
   "lat": 60.15352968,
   "lng": 24.93125407,
   "name": "Hylkeenpyytäjänkatu",
   "total": 6808,
   "origin": 3268,
   "originPercent": 0.480023502,
   "destination": 3540,
   "destinationPercent": 0.519976498
 },
 {
   "id": 66,
   "lat": 60.155309,
   "lng": 24.9591271,
   "name": "Ehrenströmintie",
   "total": 3214,
   "origin": 1610,
   "originPercent": 0.500933416,
   "destination": 1604,
   "destinationPercent": 0.499066584
 },
 {
   "id": 67,
   "lat": 60.15997725,
   "lng": 24.93383429,
   "name": "Perämiehenkatu",
   "total": 6929,
   "origin": 3480,
   "originPercent": 0.502236975,
   "destination": 3449,
   "destinationPercent": 0.497763025
 },
 {
   "id": 68,
   "lat": 60.1618359,
   "lng": 24.9368179,
   "name": "Albertinkatu",
   "total": 6738,
   "origin": 3376,
   "originPercent": 0.501038884,
   "destination": 3362,
   "destinationPercent": 0.498961116
 },
 {
   "id": 69,
   "lat": 60.1656962,
   "lng": 24.9314323,
   "name": "Kalevankatu",
   "total": 7171,
   "origin": 3590,
   "originPercent": 0.500627528,
   "destination": 3581,
   "destinationPercent": 0.499372472
 },
 {
   "id": 70,
   "lat": 60.1731473,
   "lng": 24.9224112,
   "name": "Sammonpuistikko",
   "total": 5395,
   "origin": 2726,
   "originPercent": 0.505282669,
   "destination": 2669,
   "destinationPercent": 0.494717331
 },
 {
   "id": 71,
   "lat": 60.17261155,
   "lng": 24.91127965,
   "name": "Hietaniemenkatu",
   "total": 4644,
   "origin": 2283,
   "originPercent": 0.491602067,
   "destination": 2361,
   "destinationPercent": 0.508397933
 },
 {
   "id": 72,
   "lat": 60.17558787,
   "lng": 24.91566275,
   "name": "Eteläinen Hesperiankatu",
   "total": 6354,
   "origin": 3177,
   "originPercent": 0.5,
   "destination": 3177,
   "destinationPercent": 0.5
 },
 {
   "id": 73,
   "lat": 60.1792967,
   "lng": 24.9132504,
   "name": "Kesäkatu",
   "total": 4290,
   "origin": 2145,
   "originPercent": 0.5,
   "destination": 2145,
   "destinationPercent": 0.5
 },
 {
   "id": 74,
   "lat": 60.183137,
   "lng": 24.911127,
   "name": "Rajasaarentie",
   "total": 3785,
   "origin": 1898,
   "originPercent": 0.501453104,
   "destination": 1887,
   "destinationPercent": 0.498546896
 },
 {
   "id": 75,
   "lat": 60.1838677,
   "lng": 24.9198371,
   "name": "Korjaamo",
   "total": 10094,
   "origin": 5088,
   "originPercent": 0.504061819,
   "destination": 5006,
   "destinationPercent": 0.495938181
 },
 {
   "id": 76,
   "lat": 60.1845055,
   "lng": 24.9249741,
   "name": "Olympiastadion",
   "total": 9086,
   "origin": 4413,
   "originPercent": 0.485692274,
   "destination": 4673,
   "destinationPercent": 0.514307726
 },
 {
   "id": 77,
   "lat": 60.18523633,
   "lng": 24.91724984,
   "name": "Nordenskiöldinaukio",
   "total": 5654,
   "origin": 2847,
   "originPercent": 0.503537319,
   "destination": 2807,
   "destinationPercent": 0.496462681
 },
 {
   "id": 78,
   "lat": 60.1878352,
   "lng": 24.9180102,
   "name": "Messeniuksenkatu",
   "total": 8254,
   "origin": 4129,
   "originPercent": 0.500242307,
   "destination": 4125,
   "destinationPercent": 0.499757693
 },
 {
   "id": 79,
   "lat": 60.1892172,
   "lng": 24.9292286,
   "name": "Uimastadion",
   "total": 6843,
   "origin": 3422,
   "originPercent": 0.500073067,
   "destination": 3421,
   "destinationPercent": 0.499926933
 },
 {
   "id": 80,
   "lat": 60.1894025,
   "lng": 24.9205978,
   "name": "Jäähalli",
   "total": 4885,
   "origin": 2430,
   "originPercent": 0.497441146,
   "destination": 2455,
   "destinationPercent": 0.502558854
 },
 {
   "id": 81,
   "lat": 60.1883091,
   "lng": 24.9123717,
   "name": "Stenbäckinkatu",
   "total": 3217,
   "origin": 1613,
   "originPercent": 0.501398819,
   "destination": 1604,
   "destinationPercent": 0.498601181
 },
 {
   "id": 82,
   "lat": 60.19095693,
   "lng": 24.91282714,
   "name": "Töölöntulli",
   "total": 6107,
   "origin": 3252,
   "originPercent": 0.532503684,
   "destination": 2855,
   "destinationPercent": 0.467496316
 },
 {
   "id": 83,
   "lat": 60.1902195,
   "lng": 24.9083351,
   "name": "Meilahden sairaala",
   "total": 4804,
   "origin": 2508,
   "originPercent": 0.522064946,
   "destination": 2296,
   "destinationPercent": 0.477935054
 },
 {
   "id": 84,
   "lat": 60.19120216,
   "lng": 24.89991005,
   "name": "Paciuksenkatu",
   "total": 3719,
   "origin": 1872,
   "originPercent": 0.503361119,
   "destination": 1847,
   "destinationPercent": 0.496638881
 },
 {
   "id": 85,
   "lat": 60.1934696,
   "lng": 24.905889,
   "name": "Jalavatie",
   "total": 3057,
   "origin": 1549,
   "originPercent": 0.506705921,
   "destination": 1508,
   "destinationPercent": 0.493294079
 },
 {
   "id": 86,
   "lat": 60.1952452,
   "lng": 24.9018997,
   "name": "Kuusitie",
   "total": 4516,
   "origin": 2292,
   "originPercent": 0.507528787,
   "destination": 2224,
   "destinationPercent": 0.492471213
 },
 {
   "id": 87,
   "lat": 60.18827522,
   "lng": 24.95597593,
   "name": "Kustaankatu",
   "total": 3923,
   "origin": 2227,
   "originPercent": 0.567677798,
   "destination": 1696,
   "destinationPercent": 0.432322202
 },
 {
   "id": 88,
   "lat": 60.1989402,
   "lng": 24.9012997,
   "name": "Kiskontie",
   "total": 2995,
   "origin": 1497,
   "originPercent": 0.499833055,
   "destination": 1498,
   "destinationPercent": 0.500166945
 },
 {
   "id": 89,
   "lat": 60.1975329,
   "lng": 24.899261,
   "name": "Tilkanvierto",
   "total": 6909,
   "origin": 3409,
   "originPercent": 0.493414387,
   "destination": 3500,
   "destinationPercent": 0.506585613
 },
 {
   "id": 90,
   "lat": 60.1944475,
   "lng": 24.8911179,
   "name": "Paciuksenkaari",
   "total": 4321,
   "origin": 2133,
   "originPercent": 0.493635732,
   "destination": 2188,
   "destinationPercent": 0.506364268
 },
 {
   "id": 91,
   "lat": 60.188399,
   "lng": 24.8847362,
   "name": "Seurasaari",
   "total": 3520,
   "origin": 1758,
   "originPercent": 0.499431818,
   "destination": 1762,
   "destinationPercent": 0.500568182
 },
 {
   "id": 92,
   "lat": 60.19263058,
   "lng": 24.87922144,
   "name": "Saunalahdentie",
   "total": 1705,
   "origin": 828,
   "originPercent": 0.485630499,
   "destination": 877,
   "destinationPercent": 0.514369501
 },
 {
   "id": 93,
   "lat": 60.1948358,
   "lng": 24.8713963,
   "name": "Torpanranta",
   "total": 2081,
   "origin": 1004,
   "originPercent": 0.482460356,
   "destination": 1077,
   "destinationPercent": 0.517539644
 },
 {
   "id": 94,
   "lat": 60.19793091,
   "lng": 24.87622172,
   "name": "Laajalahden aukio",
   "total": 6481,
   "origin": 3131,
   "originPercent": 0.483104459,
   "destination": 3350,
   "destinationPercent": 0.516895541
 },
 {
   "id": 95,
   "lat": 60.1967196,
   "lng": 24.8840917,
   "name": "Munkkiniemen aukio",
   "total": 4705,
   "origin": 2315,
   "originPercent": 0.492029756,
   "destination": 2390,
   "destinationPercent": 0.507970244
 },
 {
   "id": 96,
   "lat": 60.1996653,
   "lng": 24.8836209,
   "name": "Huopalahdentie",
   "total": 3255,
   "origin": 1504,
   "originPercent": 0.462058372,
   "destination": 1751,
   "destinationPercent": 0.537941628
 },
 {
   "id": 98,
   "lat": 60.2038803,
   "lng": 24.8708833,
   "name": "Ulvilantie",
   "total": 2039,
   "origin": 1035,
   "originPercent": 0.507601766,
   "destination": 1004,
   "destinationPercent": 0.492398234
 },
 {
   "id": 99,
   "lat": 60.2071193,
   "lng": 24.8559544,
   "name": "Muusantori",
   "total": 1911,
   "origin": 910,
   "originPercent": 0.476190476,
   "destination": 1001,
   "destinationPercent": 0.523809524
 },
 {
   "id": 100,
   "lat": 60.20969563,
   "lng": 24.86873948,
   "name": "Teljäntie",
   "total": 1750,
   "origin": 832,
   "originPercent": 0.475428571,
   "destination": 918,
   "destinationPercent": 0.524571429
 },
 {
   "id": 101,
   "lat": 60.2059946,
   "lng": 24.8798291,
   "name": "Munkkivuoren ostoskeskus",
   "total": 6039,
   "origin": 3023,
   "originPercent": 0.500579566,
   "destination": 3016,
   "destinationPercent": 0.499420434
 },
 {
   "id": 103,
   "lat": 60.208925,
   "lng": 24.8895209,
   "name": "Vihdintie",
   "total": 3238,
   "origin": 1620,
   "originPercent": 0.500308833,
   "destination": 1618,
   "destinationPercent": 0.499691167
 },
 {
   "id": 104,
   "lat": 60.2056785,
   "lng": 24.8916817,
   "name": "Kriikunakuja",
   "total": 2089,
   "origin": 1024,
   "originPercent": 0.490186692,
   "destination": 1065,
   "destinationPercent": 0.509813308
 },
 {
   "id": 105,
   "lat": 60.2028392,
   "lng": 24.8934761,
   "name": "Tilkantori",
   "total": 3228,
   "origin": 1597,
   "originPercent": 0.494733581,
   "destination": 1631,
   "destinationPercent": 0.505266419
 },
 {
   "id": 106,
   "lat": 60.2034735,
   "lng": 24.8989297,
   "name": "Korppaanmäentie",
   "total": 3545,
   "origin": 1776,
   "originPercent": 0.500987306,
   "destination": 1769,
   "destinationPercent": 0.499012694
 },
 {
   "id": 107,
   "lat": 60.2024393,
   "lng": 24.9054609,
   "name": "Tenholantie",
   "total": 3841,
   "origin": 1921,
   "originPercent": 0.500130174,
   "destination": 1920,
   "destinationPercent": 0.499869826
 },
 {
   "id": 108,
   "lat": 60.2044439,
   "lng": 24.91794929,
   "name": "Radiokatu",
   "total": 1445,
   "origin": 764,
   "originPercent": 0.528719723,
   "destination": 681,
   "destinationPercent": 0.471280277
 },
 {
   "id": 109,
   "lat": 60.20232752,
   "lng": 24.92263003,
   "name": "Hertanmäenkatu",
   "total": 3656,
   "origin": 1902,
   "originPercent": 0.5202407,
   "destination": 1754,
   "destinationPercent": 0.4797593
 },
 {
   "id": 110,
   "lat": 60.19890671,
   "lng": 24.92486532,
   "name": "Maistraatintori",
   "total": 1731,
   "origin": 864,
   "originPercent": 0.499133449,
   "destination": 867,
   "destinationPercent": 0.500866551
 },
 {
   "id": 111,
   "lat": 60.1975724,
   "lng": 24.9267808,
   "name": "Esterinportti",
   "total": 6356,
   "origin": 3238,
   "originPercent": 0.509439899,
   "destination": 3118,
   "destinationPercent": 0.490560101
 },
 {
   "id": 112,
   "lat": 60.2014382,
   "lng": 24.9332721,
   "name": "Rautatieläisenkatu",
   "total": 5487,
   "origin": 2751,
   "originPercent": 0.501366867,
   "destination": 2736,
   "destinationPercent": 0.498633133
 },
 {
   "id": 113,
   "lat": 60.19970941,
   "lng": 24.93520368,
   "name": "Veturitori",
   "total": 7251,
   "origin": 4388,
   "originPercent": 0.605157909,
   "destination": 2863,
   "destinationPercent": 0.394842091
 },
 {
   "id": 114,
   "lat": 60.19701385,
   "lng": 24.93588684,
   "name": "Ratapihantie",
   "total": 6327,
   "origin": 3300,
   "originPercent": 0.521574206,
   "destination": 3027,
   "destinationPercent": 0.478425794
 },
 {
   "id": 115,
   "lat": 60.1942095,
   "lng": 24.941578,
   "name": "Venttiilikuja",
   "total": 5290,
   "origin": 2706,
   "originPercent": 0.511531191,
   "destination": 2584,
   "destinationPercent": 0.488468809
 },
 {
   "id": 116,
   "lat": 60.1911411,
   "lng": 24.9401593,
   "name": "Linnanmäki",
   "total": 8824,
   "origin": 4547,
   "originPercent": 0.515299184,
   "destination": 4277,
   "destinationPercent": 0.484700816
 },
 {
   "id": 117,
   "lat": 60.1896706,
   "lng": 24.9481024,
   "name": "Brahen puistikko",
   "total": 6456,
   "origin": 3244,
   "originPercent": 0.502478315,
   "destination": 3212,
   "destinationPercent": 0.497521685
 },
 {
   "id": 118,
   "lat": 60.1895417,
   "lng": 24.9521601,
   "name": "Fleminginkatu",
   "total": 8496,
   "origin": 4307,
   "originPercent": 0.506944444,
   "destination": 4189,
   "destinationPercent": 0.493055556
 },
 {
   "id": 119,
   "lat": 60.1907096,
   "lng": 24.9568729,
   "name": "Gebhardinaukio",
   "total": 5115,
   "origin": 2665,
   "originPercent": 0.521016618,
   "destination": 2450,
   "destinationPercent": 0.478983382
 },
 {
   "id": 120,
   "lat": 60.1896352,
   "lng": 24.9635596,
   "name": "Mäkelänkatu",
   "total": 3995,
   "origin": 2272,
   "originPercent": 0.568710889,
   "destination": 1723,
   "destinationPercent": 0.431289111
 },
 {
   "id": 121,
   "lat": 60.1864633,
   "lng": 24.9678718,
   "name": "Vilhonvuorenkatu",
   "total": 12315,
   "origin": 5743,
   "originPercent": 0.46634186,
   "destination": 6572,
   "destinationPercent": 0.53365814
 },
 {
   "id": 122,
   "lat": 60.1837182,
   "lng": 24.9621936,
   "name": "Lintulahdenkatu",
   "total": 12718,
   "origin": 6128,
   "originPercent": 0.481836767,
   "destination": 6590,
   "destinationPercent": 0.518163233
 },
 {
   "id": 123,
   "lat": 60.179765,
   "lng": 24.9554618,
   "name": "Näkinsilta",
   "total": 10110,
   "origin": 5082,
   "originPercent": 0.502670623,
   "destination": 5028,
   "destinationPercent": 0.497329377
 },
 {
   "id": 124,
   "lat": 60.18265182,
   "lng": 24.98179261,
   "name": "Isoisänsilta",
   "total": 7066,
   "origin": 3378,
   "originPercent": 0.478063968,
   "destination": 3688,
   "destinationPercent": 0.521936032
 },
 {
   "id": 125,
   "lat": 60.18479903,
   "lng": 24.97864799,
   "name": "Arielinkatu",
   "total": 2390,
   "origin": 1202,
   "originPercent": 0.50292887,
   "destination": 1188,
   "destinationPercent": 0.49707113
 },
 {
   "id": 126,
   "lat": 60.18755649,
   "lng": 24.9770684,
   "name": "Kalasataman metroasema",
   "total": 17251,
   "origin": 8531,
   "originPercent": 0.494522057,
   "destination": 8720,
   "destinationPercent": 0.505477943
 },
 {
   "id": 127,
   "lat": 60.1896994,
   "lng": 24.9711926,
   "name": "Teurastamo",
   "total": 7624,
   "origin": 3679,
   "originPercent": 0.482555089,
   "destination": 3945,
   "destinationPercent": 0.517444911
 },
 {
   "id": 128,
   "lat": 60.1920576,
   "lng": 24.9642238,
   "name": "Päijänteentie",
   "total": 3676,
   "origin": 1936,
   "originPercent": 0.526659412,
   "destination": 1740,
   "destinationPercent": 0.473340588
 },
 {
   "id": 129,
   "lat": 60.1942342,
   "lng": 24.9579931,
   "name": "Pernajantie",
   "total": 5538,
   "origin": 2834,
   "originPercent": 0.511737089,
   "destination": 2704,
   "destinationPercent": 0.488262911
 },
 {
   "id": 130,
   "lat": 60.193486,
   "lng": 24.9487524,
   "name": "Teollisuuskatu",
   "total": 3409,
   "origin": 1806,
   "originPercent": 0.529774127,
   "destination": 1603,
   "destinationPercent": 0.470225873
 },
 {
   "id": 131,
   "lat": 60.1962627,
   "lng": 24.9476186,
   "name": "Elimäenkatu",
   "total": 4572,
   "origin": 2227,
   "originPercent": 0.487095363,
   "destination": 2345,
   "destinationPercent": 0.512904637
 },
 {
   "id": 132,
   "lat": 60.1958848,
   "lng": 24.9545339,
   "name": "Hollolantie",
   "total": 2998,
   "origin": 1533,
   "originPercent": 0.511340894,
   "destination": 1465,
   "destinationPercent": 0.488659106
 },
 {
   "id": 133,
   "lat": 60.1974886,
   "lng": 24.9614385,
   "name": "Paavalinpuisto",
   "total": 4545,
   "origin": 2281,
   "originPercent": 0.501870187,
   "destination": 2264,
   "destinationPercent": 0.498129813
 },
 {
   "id": 134,
   "lat": 60.1985314,
   "lng": 24.9676708,
   "name": "Haukilahdenkatu",
   "total": 6919,
   "origin": 3431,
   "originPercent": 0.495880908,
   "destination": 3488,
   "destinationPercent": 0.504119092
 },
 {
   "id": 135,
   "lat": 60.2010614,
   "lng": 24.9440506,
   "name": "Velodrominrinne",
   "total": 4273,
   "origin": 2154,
   "originPercent": 0.504095483,
   "destination": 2119,
   "destinationPercent": 0.495904517
 },
 {
   "id": 136,
   "lat": 60.2032721,
   "lng": 24.9513636,
   "name": "Sofianlehdonkatu",
   "total": 1918,
   "origin": 947,
   "originPercent": 0.493743483,
   "destination": 971,
   "destinationPercent": 0.506256517
 },
 {
   "id": 137,
   "lat": 60.2027912,
   "lng": 24.9666128,
   "name": "Arabian kauppakeskus",
   "total": 11037,
   "origin": 5349,
   "originPercent": 0.484642566,
   "destination": 5688,
   "destinationPercent": 0.515357434
 },
 {
   "id": 138,
   "lat": 60.20649156,
   "lng": 24.97707901,
   "name": "Arabiankatu",
   "total": 6107,
   "origin": 2787,
   "originPercent": 0.456361552,
   "destination": 3320,
   "destinationPercent": 0.543638448
 },
 {
   "id": 139,
   "lat": 60.21003424,
   "lng": 24.97656318,
   "name": "Kaironkatu",
   "total": 2959,
   "origin": 1448,
   "originPercent": 0.489354512,
   "destination": 1511,
   "destinationPercent": 0.510645488
 },
 {
   "id": 140,
   "lat": 60.2137007,
   "lng": 24.9797283,
   "name": "Verkatehtaanpuisto",
   "total": 2995,
   "origin": 1451,
   "originPercent": 0.484474124,
   "destination": 1544,
   "destinationPercent": 0.515525876
 },
 {
   "id": 141,
   "lat": 60.2078582,
   "lng": 24.9676383,
   "name": "Intiankatu",
   "total": 4969,
   "origin": 2487,
   "originPercent": 0.500503119,
   "destination": 2482,
   "destinationPercent": 0.499496881
 },
 {
   "id": 142,
   "lat": 60.208749,
   "lng": 24.9465139,
   "name": "Koskelantie",
   "total": 6218,
   "origin": 3128,
   "originPercent": 0.503055645,
   "destination": 3090,
   "destinationPercent": 0.496944355
 },
 {
   "id": 143,
   "lat": 60.1570856,
   "lng": 24.86930605,
   "name": "Kuikkarinne",
   "total": 3901,
   "origin": 1911,
   "originPercent": 0.489874391,
   "destination": 1990,
   "destinationPercent": 0.510125609
 },
 {
   "id": 144,
   "lat": 60.2139043,
   "lng": 24.9588108,
   "name": "Käpyläntie",
   "total": 3236,
   "origin": 1611,
   "originPercent": 0.497836836,
   "destination": 1625,
   "destinationPercent": 0.502163164
 },
 {
   "id": 145,
   "lat": 60.213421,
   "lng": 24.9437964,
   "name": "Pohjolankatu",
   "total": 1206,
   "origin": 648,
   "originPercent": 0.537313433,
   "destination": 558,
   "destinationPercent": 0.462686567
 },
 {
   "id": 146,
   "lat": 60.2172043,
   "lng": 24.9544112,
   "name": "Pohjolanaukio",
   "total": 1936,
   "origin": 995,
   "originPercent": 0.513946281,
   "destination": 941,
   "destinationPercent": 0.486053719
 },
 {
   "id": 147,
   "lat": 60.22080571,
   "lng": 24.94792902,
   "name": "Käpylän asema",
   "total": 2110,
   "origin": 1090,
   "originPercent": 0.516587678,
   "destination": 1020,
   "destinationPercent": 0.483412322
 },
 {
   "id": 148,
   "lat": 60.2184427,
   "lng": 24.9664619,
   "name": "Juhana Herttuan tie",
   "total": 3029,
   "origin": 1469,
   "originPercent": 0.484978541,
   "destination": 1560,
   "destinationPercent": 0.515021459
 },
 {
   "id": 149,
   "lat": 60.183164,
   "lng": 24.9441949,
   "name": "Toinen linja",
   "total": 4998,
   "origin": 2589,
   "originPercent": 0.518007203,
   "destination": 2409,
   "destinationPercent": 0.481992797
 },
 {
   "id": 150,
   "lat": 60.1766793,
   "lng": 24.9338701,
   "name": "Töölönlahden puisto",
   "total": 7381,
   "origin": 3688,
   "originPercent": 0.499661293,
   "destination": 3693,
   "destinationPercent": 0.500338707
 },
 {
   "id": 161,
   "lat": 60.16723083,
   "lng": 24.94746582,
   "name": "Eteläesplanadi",
   "total": 10868,
   "origin": 4868,
   "originPercent": 0.447920501,
   "destination": 6000,
   "destinationPercent": 0.552079499
 },
 {
   "id": 162,
   "lat": 60.16957343,
   "lng": 24.9265905,
   "name": "Leppäsuonaukio",
   "total": 5441,
   "origin": 2750,
   "originPercent": 0.505421797,
   "destination": 2691,
   "destinationPercent": 0.494578203
 },
 {
   "id": 163,
   "lat": 60.18147258,
   "lng": 24.85053677,
   "name": "Lehtisaarentie",
   "total": 3032,
   "origin": 1475,
   "originPercent": 0.486477573,
   "destination": 1557,
   "destinationPercent": 0.513522427
 },
 {
   "id": 200,
   "lat": 60.15039563,
   "lng": 24.91586267,
   "name": "Länsiterminaali",
   "total": 2166,
   "origin": 1022,
   "originPercent": 0.471837488,
   "destination": 1144,
   "destinationPercent": 0.528162512
 },
 {
   "id": 201,
   "lat": 60.15693191,
   "lng": 24.91220044,
   "name": "Länsisatamankuja",
   "total": 6295,
   "origin": 3140,
   "originPercent": 0.498808578,
   "destination": 3155,
   "destinationPercent": 0.501191422
 },
 {
   "id": 202,
   "lat": 60.17806593,
   "lng": 24.95845221,
   "name": "Merihaka",
   "total": 5386,
   "origin": 2667,
   "originPercent": 0.49517267,
   "destination": 2719,
   "destinationPercent": 0.50482733
 },
 {
   "id": 203,
   "lat": 60.19923543,
   "lng": 24.93782637,
   "name": "Opastinsilta",
   "total": 4582,
   "origin": 2957,
   "originPercent": 0.645351375,
   "destination": 1625,
   "destinationPercent": 0.354648625
 },
 {
   "id": 204,
   "lat": 60.20567461,
   "lng": 24.96236745,
   "name": "A.I. Virtasen aukio",
   "total": 2769,
   "origin": 1425,
   "originPercent": 0.514626219,
   "destination": 1344,
   "destinationPercent": 0.485373781
 },
 {
   "id": 205,
   "lat": 60.20662644,
   "lng": 24.92221989,
   "name": "Ilmalan asema",
   "total": 881,
   "origin": 513,
   "originPercent": 0.582292849,
   "destination": 368,
   "destinationPercent": 0.417707151
 },
 {
   "id": 206,
   "lat": 60.20767996,
   "lng": 24.89866789,
   "name": "Ruskeasuon varikko",
   "total": 1611,
   "origin": 805,
   "originPercent": 0.499689634,
   "destination": 806,
   "destinationPercent": 0.500310366
 },
 {
   "id": 207,
   "lat": 60.2110753,
   "lng": 24.88166025,
   "name": "Vanha Viertotie",
   "total": 1818,
   "origin": 922,
   "originPercent": 0.507150715,
   "destination": 896,
   "destinationPercent": 0.492849285
 },
 {
   "id": 208,
   "lat": 60.21592224,
   "lng": 24.87646479,
   "name": "Valimotie",
   "total": 3217,
   "origin": 1557,
   "originPercent": 0.483991296,
   "destination": 1660,
   "destinationPercent": 0.516008704
 },
 {
   "id": 209,
   "lat": 60.21785454,
   "lng": 24.87053957,
   "name": "Takomotie",
   "total": 2533,
   "origin": 1245,
   "originPercent": 0.491512041,
   "destination": 1288,
   "destinationPercent": 0.508487959
 },
 {
   "id": 210,
   "lat": 60.21880736,
   "lng": 24.85566795,
   "name": "Pajamäki",
   "total": 1417,
   "origin": 710,
   "originPercent": 0.501058574,
   "destination": 707,
   "destinationPercent": 0.498941426
 },
 {
   "id": 211,
   "lat": 60.21227524,
   "lng": 24.89955114,
   "name": "Haagan tori",
   "total": 2265,
   "origin": 1099,
   "originPercent": 0.485209713,
   "destination": 1166,
   "destinationPercent": 0.514790287
 },
 {
   "id": 212,
   "lat": 60.21661654,
   "lng": 24.8995437,
   "name": "Tunnelitie",
   "total": 2219,
   "origin": 1106,
   "originPercent": 0.498422713,
   "destination": 1113,
   "destinationPercent": 0.501577287
 },
 {
   "id": 213,
   "lat": 60.21808856,
   "lng": 24.89505934,
   "name": "Huopalahden asema",
   "total": 3103,
   "origin": 1557,
   "originPercent": 0.501772478,
   "destination": 1546,
   "destinationPercent": 0.498227522
 },
 {
   "id": 214,
   "lat": 60.22229428,
   "lng": 24.87587091,
   "name": "Valimon asema",
   "total": 1588,
   "origin": 799,
   "originPercent": 0.503148615,
   "destination": 789,
   "destinationPercent": 0.496851385
 },
 {
   "id": 215,
   "lat": 60.22431429,
   "lng": 24.85863812,
   "name": "Pitäjänmäen asema",
   "total": 1406,
   "origin": 714,
   "originPercent": 0.507823613,
   "destination": 692,
   "destinationPercent": 0.492176387
 },
 {
   "id": 216,
   "lat": 60.22676996,
   "lng": 24.85354096,
   "name": "Jännetie",
   "total": 1269,
   "origin": 638,
   "originPercent": 0.502758077,
   "destination": 631,
   "destinationPercent": 0.497241923
 },
 {
   "id": 217,
   "lat": 60.22714323,
   "lng": 24.87322737,
   "name": "Marttila",
   "total": 745,
   "origin": 376,
   "originPercent": 0.504697987,
   "destination": 369,
   "destinationPercent": 0.495302013
 },
 {
   "id": 218,
   "lat": 60.2301515,
   "lng": 24.88312885,
   "name": "Pohjois-Haagan asema",
   "total": 1832,
   "origin": 916,
   "originPercent": 0.5,
   "destination": 916,
   "destinationPercent": 0.5
 },
 {
   "id": 219,
   "lat": 60.23285214,
   "lng": 24.88743456,
   "name": "Näyttelijäntie",
   "total": 1085,
   "origin": 540,
   "originPercent": 0.497695853,
   "destination": 545,
   "destinationPercent": 0.502304147
 },
 {
   "id": 220,
   "lat": 60.22940882,
   "lng": 24.89201141,
   "name": "Ida Aalbergin tie",
   "total": 1173,
   "origin": 586,
   "originPercent": 0.499573743,
   "destination": 587,
   "destinationPercent": 0.500426257
 },
 {
   "id": 221,
   "lat": 60.22534052,
   "lng": 24.89479265,
   "name": "Thalianaukio",
   "total": 1283,
   "origin": 645,
   "originPercent": 0.502727981,
   "destination": 638,
   "destinationPercent": 0.497272019
 },
 {
   "id": 222,
   "lat": 60.22197554,
   "lng": 24.90328665,
   "name": "Huovitie",
   "total": 1102,
   "origin": 551,
   "originPercent": 0.5,
   "destination": 551,
   "destinationPercent": 0.5
 },
 {
   "id": 223,
   "lat": 60.2274694,
   "lng": 24.90644356,
   "name": "Hämeenlinnanväylä",
   "total": 862,
   "origin": 432,
   "originPercent": 0.501160093,
   "destination": 430,
   "destinationPercent": 0.498839907
 },
 {
   "id": 224,
   "lat": 60.22794237,
   "lng": 24.92656476,
   "name": "Vesakkotie",
   "total": 1042,
   "origin": 511,
   "originPercent": 0.490403071,
   "destination": 531,
   "destinationPercent": 0.509596929
 },
 {
   "id": 225,
   "lat": 60.23131987,
   "lng": 24.93504884,
   "name": "Maunula",
   "total": 1307,
   "origin": 656,
   "originPercent": 0.501912777,
   "destination": 651,
   "destinationPercent": 0.498087223
 },
 {
   "id": 226,
   "lat": 60.23910894,
   "lng": 24.92859502,
   "name": "Lepolantie",
   "total": 788,
   "origin": 374,
   "originPercent": 0.474619289,
   "destination": 414,
   "destinationPercent": 0.525380711
 },
 {
   "id": 227,
   "lat": 60.22440378,
   "lng": 24.95256124,
   "name": "Kylävoudintie",
   "total": 1179,
   "origin": 589,
   "originPercent": 0.499575912,
   "destination": 590,
   "destinationPercent": 0.500424088
 },
 {
   "id": 228,
   "lat": 60.2303917,
   "lng": 24.94838914,
   "name": "Kustaankartano",
   "total": 995,
   "origin": 514,
   "originPercent": 0.516582915,
   "destination": 481,
   "destinationPercent": 0.483417085
 },
 {
   "id": 229,
   "lat": 60.23268692,
   "lng": 24.95876153,
   "name": "Käskynhaltijantie",
   "total": 759,
   "origin": 417,
   "originPercent": 0.549407115,
   "destination": 342,
   "destinationPercent": 0.450592885
 },
 {
   "id": 230,
   "lat": 60.228926,
   "lng": 24.96355034,
   "name": "Mäkitorpantie",
   "total": 541,
   "origin": 266,
   "originPercent": 0.49168207,
   "destination": 275,
   "destinationPercent": 0.50831793
 },
 {
   "id": 231,
   "lat": 60.23370686,
   "lng": 24.96539508,
   "name": "Siltavoudintie",
   "total": 752,
   "origin": 393,
   "originPercent": 0.522606383,
   "destination": 359,
   "destinationPercent": 0.477393617
 },
 {
   "id": 232,
   "lat": 60.22869895,
   "lng": 24.96760861,
   "name": "Oulunkylän asema",
   "total": 3196,
   "origin": 1586,
   "originPercent": 0.496245307,
   "destination": 1610,
   "destinationPercent": 0.503754693
 },
 {
   "id": 233,
   "lat": 60.22493036,
   "lng": 24.97281937,
   "name": "Kirkkoherrantie",
   "total": 734,
   "origin": 374,
   "originPercent": 0.509536785,
   "destination": 360,
   "destinationPercent": 0.490463215
 },
 {
   "id": 234,
   "lat": 60.23178407,
   "lng": 24.97813892,
   "name": "Otto Brandtin tie",
   "total": 1389,
   "origin": 632,
   "originPercent": 0.4550036,
   "destination": 757,
   "destinationPercent": 0.5449964
 },
 {
   "id": 235,
   "lat": 60.21721481,
   "lng": 24.98442008,
   "name": "Katariina Saksilaisen katu",
   "total": 1826,
   "origin": 857,
   "originPercent": 0.469331873,
   "destination": 969,
   "destinationPercent": 0.530668127
 },
 {
   "id": 236,
   "lat": 60.22421214,
   "lng": 24.98860012,
   "name": "Hernepellontie",
   "total": 900,
   "origin": 437,
   "originPercent": 0.485555556,
   "destination": 463,
   "destinationPercent": 0.514444444
 },
 {
   "id": 237,
   "lat": 60.23030193,
   "lng": 24.99853382,
   "name": "Aulangontie",
   "total": 739,
   "origin": 376,
   "originPercent": 0.50879567,
   "destination": 363,
   "destinationPercent": 0.49120433
 },
 {
   "id": 238,
   "lat": 60.23457857,
   "lng": 25.01031391,
   "name": "Pihlajamäki",
   "total": 665,
   "origin": 331,
   "originPercent": 0.497744361,
   "destination": 334,
   "destinationPercent": 0.502255639
 },
 {
   "id": 239,
   "lat": 60.22752067,
   "lng": 25.01006206,
   "name": "Viikin tiedepuisto",
   "total": 3633,
   "origin": 1800,
   "originPercent": 0.495458299,
   "destination": 1833,
   "destinationPercent": 0.504541701
 },
 {
   "id": 240,
   "lat": 60.2274953,
   "lng": 25.02761893,
   "name": "Viikin normaalikoulu",
   "total": 1658,
   "origin": 699,
   "originPercent": 0.42159228,
   "destination": 959,
   "destinationPercent": 0.57840772
 },
 {
   "id": 241,
   "lat": 60.23405301,
   "lng": 25.0328574,
   "name": "Agronominkatu",
   "total": 1102,
   "origin": 472,
   "originPercent": 0.42831216,
   "destination": 630,
   "destinationPercent": 0.57168784
 },
 {
   "id": 242,
   "lat": 60.23033718,
   "lng": 25.04356807,
   "name": "Von Daehnin katu",
   "total": 635,
   "origin": 306,
   "originPercent": 0.481889764,
   "destination": 329,
   "destinationPercent": 0.518110236
 },
 {
   "id": 243,
   "lat": 60.18186178,
   "lng": 24.99203711,
   "name": "Mustikkamaa",
   "total": 2529,
   "origin": 1253,
   "originPercent": 0.495452748,
   "destination": 1276,
   "destinationPercent": 0.504547252
 },
 {
   "id": 244,
   "lat": 60.1858875,
   "lng": 25.00601922,
   "name": "Relanderinaukio",
   "total": 1398,
   "origin": 724,
   "originPercent": 0.51788269,
   "destination": 674,
   "destinationPercent": 0.48211731
 },
 {
   "id": 245,
   "lat": 60.18895009,
   "lng": 25.00656653,
   "name": "Kulosaaren metroasema",
   "total": 3418,
   "origin": 1726,
   "originPercent": 0.504973669,
   "destination": 1692,
   "destinationPercent": 0.495026331
 },
 {
   "id": 246,
   "lat": 60.18799818,
   "lng": 25.01539165,
   "name": "Tupasaarentie",
   "total": 1127,
   "origin": 525,
   "originPercent": 0.465838509,
   "destination": 602,
   "destinationPercent": 0.534161491
 },
 {
   "id": 247,
   "lat": 60.16886856,
   "lng": 25.02086096,
   "name": "Haakoninlahdenkatu",
   "total": 402,
   "origin": 187,
   "originPercent": 0.465174129,
   "destination": 215,
   "destinationPercent": 0.534825871
 },
 {
   "id": 248,
   "lat": 60.17198027,
   "lng": 25.03296885,
   "name": "Gunillantie",
   "total": 754,
   "origin": 335,
   "originPercent": 0.444297082,
   "destination": 419,
   "destinationPercent": 0.555702918
 },
 {
   "id": 249,
   "lat": 60.17549032,
   "lng": 25.04490071,
   "name": "Isosaarentie",
   "total": 775,
   "origin": 379,
   "originPercent": 0.489032258,
   "destination": 396,
   "destinationPercent": 0.510967742
 },
 {
   "id": 250,
   "lat": 60.1677305,
   "lng": 25.04749626,
   "name": "Reiherintie",
   "total": 767,
   "origin": 356,
   "originPercent": 0.464146023,
   "destination": 411,
   "destinationPercent": 0.535853977
 },
 {
   "id": 251,
   "lat": 60.18009214,
   "lng": 25.05188371,
   "name": "Laajasalon ostoskeskus",
   "total": 1537,
   "origin": 766,
   "originPercent": 0.498373455,
   "destination": 771,
   "destinationPercent": 0.501626545
 },
 {
   "id": 252,
   "lat": 60.18374385,
   "lng": 25.05303786,
   "name": "Humalniementie",
   "total": 560,
   "origin": 283,
   "originPercent": 0.505357143,
   "destination": 277,
   "destinationPercent": 0.494642857
 },
 {
   "id": 253,
   "lat": 60.19164688,
   "lng": 25.06118417,
   "name": "Tammisalon aukio",
   "total": 1358,
   "origin": 589,
   "originPercent": 0.433726068,
   "destination": 769,
   "destinationPercent": 0.566273932
 },
 {
   "id": 254,
   "lat": 60.18723412,
   "lng": 25.03641229,
   "name": "Agnetankuja",
   "total": 2613,
   "origin": 1286,
   "originPercent": 0.492154612,
   "destination": 1327,
   "destinationPercent": 0.507845388
 },
 {
   "id": 255,
   "lat": 60.1879581,
   "lng": 25.03138531,
   "name": "Laivalahden puistotie",
   "total": 2166,
   "origin": 1048,
   "originPercent": 0.483841182,
   "destination": 1118,
   "destinationPercent": 0.516158818
 },
 {
   "id": 256,
   "lat": 60.19021015,
   "lng": 25.02606571,
   "name": "Herttoniemen ranta",
   "total": 1628,
   "origin": 837,
   "originPercent": 0.514127764,
   "destination": 791,
   "destinationPercent": 0.485872236
 },
 {
   "id": 257,
   "lat": 60.19100958,
   "lng": 25.03707004,
   "name": "Margareetankuja",
   "total": 918,
   "origin": 486,
   "originPercent": 0.529411765,
   "destination": 432,
   "destinationPercent": 0.470588235
 },
 {
   "id": 258,
   "lat": 60.1927079,
   "lng": 25.04258028,
   "name": "Abraham Wetterin tie",
   "total": 2169,
   "origin": 1097,
   "originPercent": 0.505763024,
   "destination": 1072,
   "destinationPercent": 0.494236976
 },
 {
   "id": 259,
   "lat": 60.19313763,
   "lng": 25.03111194,
   "name": "Petter Wetterin tie",
   "total": 4973,
   "origin": 2440,
   "originPercent": 0.490649507,
   "destination": 2533,
   "destinationPercent": 0.509350493
 },
 {
   "id": 260,
   "lat": 60.19461462,
   "lng": 25.02887208,
   "name": "Herttoniemen metroasema",
   "total": 6394,
   "origin": 3264,
   "originPercent": 0.510478574,
   "destination": 3130,
   "destinationPercent": 0.489521426
 },
 {
   "id": 261,
   "lat": 60.19912714,
   "lng": 25.04259247,
   "name": "Asentajanpuisto",
   "total": 1217,
   "origin": 594,
   "originPercent": 0.488085456,
   "destination": 623,
   "destinationPercent": 0.511914544
 },
 {
   "id": 262,
   "lat": 60.20596245,
   "lng": 25.04516116,
   "name": "Siilitien metroasema",
   "total": 3359,
   "origin": 1569,
   "originPercent": 0.467103305,
   "destination": 1790,
   "destinationPercent": 0.532896695
 },
 {
   "id": 263,
   "lat": 60.19844295,
   "lng": 25.03211213,
   "name": "Herttoniemen kirkko",
   "total": 958,
   "origin": 549,
   "originPercent": 0.573068894,
   "destination": 409,
   "destinationPercent": 0.426931106
 },
 {
   "id": 264,
   "lat": 60.20456166,
   "lng": 25.03359741,
   "name": "Eränkävijäntori",
   "total": 1600,
   "origin": 853,
   "originPercent": 0.533125,
   "destination": 747,
   "destinationPercent": 0.466875
 },
 {
   "id": 265,
   "lat": 60.20947671,
   "lng": 25.03748222,
   "name": "Siilitie 9",
   "total": 708,
   "origin": 388,
   "originPercent": 0.548022599,
   "destination": 320,
   "destinationPercent": 0.451977401
 },
 {
   "id": 266,
   "lat": 60.21506337,
   "lng": 25.04379378,
   "name": "Siilitie 13",
   "total": 686,
   "origin": 413,
   "originPercent": 0.602040816,
   "destination": 273,
   "destinationPercent": 0.397959184
 },
 {
   "id": 267,
   "lat": 60.2092346,
   "lng": 25.05617409,
   "name": "Roihupelto",
   "total": 1784,
   "origin": 877,
   "originPercent": 0.491591928,
   "destination": 907,
   "destinationPercent": 0.508408072
 },
 {
   "id": 268,
   "lat": 60.19553972,
   "lng": 25.05358094,
   "name": "Porolahden koulu",
   "total": 1831,
   "origin": 880,
   "originPercent": 0.480611688,
   "destination": 951,
   "destinationPercent": 0.519388312
 },
 {
   "id": 269,
   "lat": 60.1987055,
   "lng": 25.05854933,
   "name": "Peukaloisentie",
   "total": 926,
   "origin": 477,
   "originPercent": 0.51511879,
   "destination": 449,
   "destinationPercent": 0.48488121
 },
 {
   "id": 270,
   "lat": 60.20207299,
   "lng": 25.0600466,
   "name": "Tulisuontie",
   "total": 1524,
   "origin": 797,
   "originPercent": 0.522965879,
   "destination": 727,
   "destinationPercent": 0.477034121
 },
 {
   "id": 271,
   "lat": 60.20634023,
   "lng": 25.06009233,
   "name": "Prinsessantie",
   "total": 958,
   "origin": 521,
   "originPercent": 0.543841336,
   "destination": 437,
   "destinationPercent": 0.456158664
 },
 {
   "id": 272,
   "lat": 60.20432489,
   "lng": 25.07606936,
   "name": "Marjaniementie",
   "total": 1728,
   "origin": 853,
   "originPercent": 0.493634259,
   "destination": 875,
   "destinationPercent": 0.506365741
 },
 {
   "id": 273,
   "lat": 60.20709746,
   "lng": 25.07915481,
   "name": "Kauppakartanonkuja",
   "total": 513,
   "origin": 258,
   "originPercent": 0.502923977,
   "destination": 255,
   "destinationPercent": 0.497076023
 },
 {
   "id": 274,
   "lat": 60.2089976,
   "lng": 25.08678211,
   "name": "Voikukantie",
   "total": 1727,
   "origin": 888,
   "originPercent": 0.51418645,
   "destination": 839,
   "destinationPercent": 0.48581355
 },
 {
   "id": 275,
   "lat": 60.20960067,
   "lng": 25.07596802,
   "name": "Itäkeskuksen metroasema",
   "total": 3067,
   "origin": 1540,
   "originPercent": 0.502119335,
   "destination": 1527,
   "destinationPercent": 0.497880665
 },
 {
   "id": 276,
   "lat": 60.21249417,
   "lng": 25.08232209,
   "name": "Puotinharju",
   "total": 1174,
   "origin": 590,
   "originPercent": 0.502555366,
   "destination": 584,
   "destinationPercent": 0.497444634
 },
 {
   "id": 277,
   "lat": 60.20360956,
   "lng": 25.08629616,
   "name": "Marjaniemi",
   "total": 599,
   "origin": 286,
   "originPercent": 0.477462437,
   "destination": 313,
   "destinationPercent": 0.522537563
 },
 {
   "id": 278,
   "lat": 60.20905963,
   "lng": 25.10042606,
   "name": "Puotilantie",
   "total": 763,
   "origin": 383,
   "originPercent": 0.501965924,
   "destination": 380,
   "destinationPercent": 0.498034076
 },
 {
   "id": 279,
   "lat": 60.21250991,
   "lng": 25.10619874,
   "name": "Puotinkylän kartano",
   "total": 1340,
   "origin": 652,
   "originPercent": 0.486567164,
   "destination": 688,
   "destinationPercent": 0.513432836
 },
 {
   "id": 280,
   "lat": 60.21270057,
   "lng": 25.09555951,
   "name": "Puotilan ostoskeskus",
   "total": 1273,
   "origin": 611,
   "originPercent": 0.479968578,
   "destination": 662,
   "destinationPercent": 0.520031422
 },
 {
   "id": 281,
   "lat": 60.21482071,
   "lng": 25.09112453,
   "name": "Puotilan metroasema",
   "total": 1817,
   "origin": 871,
   "originPercent": 0.479361585,
   "destination": 946,
   "destinationPercent": 0.520638415
 },
 {
   "id": 282,
   "lat": 60.21860148,
   "lng": 25.10232485,
   "name": "Karhulantie",
   "total": 866,
   "origin": 395,
   "originPercent": 0.456120092,
   "destination": 471,
   "destinationPercent": 0.543879908
 },
 {
   "id": 283,
   "lat": 60.21985097,
   "lng": 25.07747024,
   "name": "Alakiventie",
   "total": 606,
   "origin": 300,
   "originPercent": 0.495049505,
   "destination": 306,
   "destinationPercent": 0.504950495
 },
 {
   "id": 284,
   "lat": 60.22408647,
   "lng": 25.07539579,
   "name": "Myllypuron metroasema",
   "total": 1545,
   "origin": 804,
   "originPercent": 0.52038835,
   "destination": 741,
   "destinationPercent": 0.47961165
 },
 {
   "id": 285,
   "lat": 60.2235652,
   "lng": 25.06542184,
   "name": "Orpaanporras",
   "total": 989,
   "origin": 520,
   "originPercent": 0.52578362,
   "destination": 469,
   "destinationPercent": 0.47421638
 },
 {
   "id": 286,
   "lat": 60.21825197,
   "lng": 25.05910388,
   "name": "Mamsellimyllynkatu",
   "total": 527,
   "origin": 270,
   "originPercent": 0.512333966,
   "destination": 257,
   "destinationPercent": 0.487666034
 },
 {
   "id": 501,
   "lat": 60.16582,
   "lng": 24.840319,
   "name": "Hanasaari",
   "total": 1246,
   "origin": 629,
   "originPercent": 0.504815409,
   "destination": 617,
   "destinationPercent": 0.495184591
 },
 {
   "id": 503,
   "lat": 60.171524,
   "lng": 24.827467,
   "name": "Keilalahti",
   "total": 1888,
   "origin": 948,
   "originPercent": 0.502118644,
   "destination": 940,
   "destinationPercent": 0.497881356
 },
 {
   "id": 505,
   "lat": 60.168266,
   "lng": 24.805758,
   "name": "Westendinasema",
   "total": 1566,
   "origin": 808,
   "originPercent": 0.51596424,
   "destination": 758,
   "destinationPercent": 0.48403576
 },
 {
   "id": 507,
   "lat": 60.168143,
   "lng": 24.796136,
   "name": "Golfpolku",
   "total": 590,
   "origin": 293,
   "originPercent": 0.496610169,
   "destination": 297,
   "destinationPercent": 0.503389831
 },
 {
   "id": 509,
   "lat": 60.171551,
   "lng": 24.802938,
   "name": "Revontulentie",
   "total": 1490,
   "origin": 764,
   "originPercent": 0.512751678,
   "destination": 726,
   "destinationPercent": 0.487248322
 },
 {
   "id": 511,
   "lat": 60.173424,
   "lng": 24.810688,
   "name": "Sateentie",
   "total": 1436,
   "origin": 730,
   "originPercent": 0.508356546,
   "destination": 706,
   "destinationPercent": 0.491643454
 },
 {
   "id": 513,
   "lat": 60.173567,
   "lng": 24.79139,
   "name": "Hakalehto",
   "total": 1534,
   "origin": 767,
   "originPercent": 0.5,
   "destination": 767,
   "destinationPercent": 0.5
 },
 {
   "id": 515,
   "lat": 60.175769,
   "lng": 24.792559,
   "name": "Oravannahkatori",
   "total": 1294,
   "origin": 702,
   "originPercent": 0.542503864,
   "destination": 592,
   "destinationPercent": 0.457496136
 },
 {
   "id": 517,
   "lat": 60.175358,
   "lng": 24.802049,
   "name": "Länsituuli",
   "total": 3772,
   "origin": 1903,
   "originPercent": 0.504506893,
   "destination": 1869,
   "destinationPercent": 0.495493107
 },
 {
   "id": 518,
   "lat": 60.174144,
   "lng": 24.806051,
   "name": "Tuulimäki",
   "total": 581,
   "origin": 292,
   "originPercent": 0.502581756,
   "destination": 289,
   "destinationPercent": 0.497418244
 },
 {
   "id": 519,
   "lat": 60.176168,
   "lng": 24.805825,
   "name": "Tapionaukio",
   "total": 2250,
   "origin": 1152,
   "originPercent": 0.512,
   "destination": 1098,
   "destinationPercent": 0.488
 },
 {
   "id": 521,
   "lat": 60.177588,
   "lng": 24.803942,
   "name": "Kulttuuriaukio",
   "total": 1929,
   "origin": 989,
   "originPercent": 0.512700881,
   "destination": 940,
   "destinationPercent": 0.487299119
 },
 {
   "id": 523,
   "lat": 60.17875,
   "lng": 24.797984,
   "name": "Ahertajantie",
   "total": 1446,
   "origin": 723,
   "originPercent": 0.5,
   "destination": 723,
   "destinationPercent": 0.5
 },
 {
   "id": 525,
   "lat": 60.178702,
   "lng": 24.810974,
   "name": "Mäntyviita",
   "total": 1819,
   "origin": 902,
   "originPercent": 0.495876855,
   "destination": 917,
   "destinationPercent": 0.504123145
 },
 {
   "id": 527,
   "lat": 60.178655,
   "lng": 24.817423,
   "name": "Otsolahti",
   "total": 1971,
   "origin": 978,
   "originPercent": 0.496194825,
   "destination": 993,
   "destinationPercent": 0.503805175
 },
 {
   "id": 529,
   "lat": 60.175233,
   "lng": 24.82895,
   "name": "Keilaniemi (M)",
   "total": 2828,
   "origin": 1411,
   "originPercent": 0.49893918,
   "destination": 1417,
   "destinationPercent": 0.50106082
 },
 {
   "id": 531,
   "lat": 60.178762,
   "lng": 24.835132,
   "name": "Keilaranta",
   "total": 1971,
   "origin": 997,
   "originPercent": 0.505834602,
   "destination": 974,
   "destinationPercent": 0.494165398
 },
 {
   "id": 532,
   "lat": 60.180027,
   "lng": 24.831804,
   "name": "Betonimies",
   "total": 1079,
   "origin": 544,
   "originPercent": 0.504170528,
   "destination": 535,
   "destinationPercent": 0.495829472
 },
 {
   "id": 533,
   "lat": 60.180806,
   "lng": 24.824747,
   "name": "Tekniikantie",
   "total": 2216,
   "origin": 1115,
   "originPercent": 0.503158845,
   "destination": 1101,
   "destinationPercent": 0.496841155
 },
 {
   "id": 537,
   "lat": 60.185096,
   "lng": 24.81422,
   "name": "Innopoli",
   "total": 1168,
   "origin": 591,
   "originPercent": 0.505993151,
   "destination": 577,
   "destinationPercent": 0.494006849
 },
 {
   "id": 538,
   "lat": 60.18363,
   "lng": 24.817403,
   "name": "Hagalundinpuisto",
   "total": 755,
   "origin": 378,
   "originPercent": 0.500662252,
   "destination": 377,
   "destinationPercent": 0.499337748
 },
 {
   "id": 539,
   "lat": 60.184987,
   "lng": 24.820099,
   "name": "Aalto-yliopisto (M), Tietotie",
   "total": 3939,
   "origin": 2008,
   "originPercent": 0.509774054,
   "destination": 1931,
   "destinationPercent": 0.490225946
 },
 {
   "id": 541,
   "lat": 60.184312,
   "lng": 24.826671,
   "name": "Aalto-yliopisto (M), Korkeakouluaukio",
   "total": 14002,
   "origin": 7217,
   "originPercent": 0.515426368,
   "destination": 6785,
   "destinationPercent": 0.484573632
 },
 {
   "id": 543,
   "lat": 60.18483,
   "lng": 24.837133,
   "name": "Otaranta",
   "total": 3584,
   "origin": 1760,
   "originPercent": 0.491071429,
   "destination": 1824,
   "destinationPercent": 0.508928571
 },
 {
   "id": 545,
   "lat": 60.188499,
   "lng": 24.829985,
   "name": "Sähkömies",
   "total": 1611,
   "origin": 817,
   "originPercent": 0.507138423,
   "destination": 794,
   "destinationPercent": 0.492861577
 },
 {
   "id": 547,
   "lat": 60.188118,
   "lng": 24.835033,
   "name": "Jämeräntaival",
   "total": 6758,
   "origin": 3424,
   "originPercent": 0.506658775,
   "destination": 3334,
   "destinationPercent": 0.493341225
 },
 {
   "id": 549,
   "lat": 60.187261,
   "lng": 24.810199,
   "name": "Maarinranta",
   "total": 1372,
   "origin": 623,
   "originPercent": 0.454081633,
   "destination": 749,
   "destinationPercent": 0.545918367
 },
 {
   "id": 551,
   "lat": 60.189143,
   "lng": 24.807083,
   "name": "Tietäjä",
   "total": 1554,
   "origin": 809,
   "originPercent": 0.520592021,
   "destination": 745,
   "destinationPercent": 0.479407979
 },
 {
   "id": 553,
   "lat": 60.186731,
   "lng": 24.806152,
   "name": "Metsänneidonpolku",
   "total": 2546,
   "origin": 1269,
   "originPercent": 0.498428908,
   "destination": 1277,
   "destinationPercent": 0.501571092
 },
 {
   "id": 555,
   "lat": 60.184765,
   "lng": 24.804022,
   "name": "Kalevalantie",
   "total": 1762,
   "origin": 872,
   "originPercent": 0.494892168,
   "destination": 890,
   "destinationPercent": 0.505107832
 },
 {
   "id": 557,
   "lat": 60.18715,
   "lng": 24.796959,
   "name": "Louhentori",
   "total": 1744,
   "origin": 871,
   "originPercent": 0.499426606,
   "destination": 873,
   "destinationPercent": 0.500573394
 },
 {
   "id": 559,
   "lat": 60.18288,
   "lng": 24.794014,
   "name": "Pohjankulma",
   "total": 2294,
   "origin": 1146,
   "originPercent": 0.49956408,
   "destination": 1148,
   "destinationPercent": 0.50043592
 },
 {
   "id": 561,
   "lat": 60.182976,
   "lng": 24.78576,
   "name": "Koivu-Mankkaa",
   "total": 782,
   "origin": 396,
   "originPercent": 0.506393862,
   "destination": 386,
   "destinationPercent": 0.493606138
 },
 {
   "id": 563,
   "lat": 60.188706,
   "lng": 24.780478,
   "name": "Mankkaanlaaksontie",
   "total": 931,
   "origin": 463,
   "originPercent": 0.497314715,
   "destination": 468,
   "destinationPercent": 0.502685285
 },
 {
   "id": 565,
   "lat": 60.194599,
   "lng": 24.769021,
   "name": "Mankkaanaukio",
   "total": 822,
   "origin": 372,
   "originPercent": 0.452554745,
   "destination": 450,
   "destinationPercent": 0.547445255
 },
 {
   "id": 571,
   "lat": 60.177749,
   "lng": 24.784654,
   "name": "Tapiolan urheilupuisto",
   "total": 1617,
   "origin": 793,
   "originPercent": 0.490414348,
   "destination": 824,
   "destinationPercent": 0.509585652
 },
 {
   "id": 573,
   "lat": 60.17465,
   "lng": 24.779428,
   "name": "Urheilupuisto (M)",
   "total": 6037,
   "origin": 3042,
   "originPercent": 0.503892662,
   "destination": 2995,
   "destinationPercent": 0.496107338
 },
 {
   "id": 575,
   "lat": 60.176107,
   "lng": 24.769667,
   "name": "Tontunmäentie",
   "total": 1234,
   "origin": 606,
   "originPercent": 0.4910859,
   "destination": 628,
   "destinationPercent": 0.5089141
 },
 {
   "id": 577,
   "lat": 60.180848,
   "lng": 24.760606,
   "name": "Olarinluoma",
   "total": 1008,
   "origin": 443,
   "originPercent": 0.439484127,
   "destination": 565,
   "destinationPercent": 0.560515873
 },
 {
   "id": 579,
   "lat": 60.171127,
   "lng": 24.775913,
   "name": "Niittymaa",
   "total": 3322,
   "origin": 1669,
   "originPercent": 0.502408188,
   "destination": 1653,
   "destinationPercent": 0.497591812
 },
 {
   "id": 581,
   "lat": 60.170758,
   "lng": 24.763184,
   "name": "Niittykumpu (M)",
   "total": 6552,
   "origin": 3338,
   "originPercent": 0.509462759,
   "destination": 3214,
   "destinationPercent": 0.490537241
 },
 {
   "id": 583,
   "lat": 60.166481,
   "lng": 24.772708,
   "name": "Haukilahdenkatu",
   "total": 1638,
   "origin": 812,
   "originPercent": 0.495726496,
   "destination": 826,
   "destinationPercent": 0.504273504
 },
 {
   "id": 585,
   "lat": 60.162396,
   "lng": 24.775882,
   "name": "Haukilahdenaukio",
   "total": 1692,
   "origin": 756,
   "originPercent": 0.446808511,
   "destination": 936,
   "destinationPercent": 0.553191489
 },
 {
   "id": 587,
   "lat": 60.162477,
   "lng": 24.767831,
   "name": "Hauenkallio",
   "total": 619,
   "origin": 322,
   "originPercent": 0.520193861,
   "destination": 297,
   "destinationPercent": 0.479806139
 },
 {
   "id": 589,
   "lat": 60.158048,
   "lng": 24.769864,
   "name": "Haukilahdenranta",
   "total": 1098,
   "origin": 485,
   "originPercent": 0.441712204,
   "destination": 613,
   "destinationPercent": 0.558287796
 },
 {
   "id": 591,
   "lat": 60.154941,
   "lng": 24.773993,
   "name": "Mellstenintie",
   "total": 1610,
   "origin": 792,
   "originPercent": 0.491925466,
   "destination": 818,
   "destinationPercent": 0.508074534
 },
 {
   "id": 593,
   "lat": 60.159601,
   "lng": 24.782536,
   "name": "Toppelundintie",
   "total": 800,
   "origin": 388,
   "originPercent": 0.485,
   "destination": 412,
   "destinationPercent": 0.515
 },
 {
   "id": 595,
   "lat": 60.158194,
   "lng": 24.791754,
   "name": "Westendintie",
   "total": 679,
   "origin": 324,
   "originPercent": 0.477172312,
   "destination": 355,
   "destinationPercent": 0.522827688
 },
 {
   "id": 596,
   "lat": 60.1624471,
   "lng": 24.7848628,
   "name": "Toppelundinportti",
   "total": 89,
   "origin": 35,
   "originPercent": 0.393258427,
   "destination": 54,
   "destinationPercent": 0.606741573
 },
 {
   "id": 597,
   "lat": 60.1637,
   "lng": 24.790132,
   "name": "Linnakepolku",
   "total": 1211,
   "origin": 578,
   "originPercent": 0.477291495,
   "destination": 633,
   "destinationPercent": 0.522708505
 },
 {
   "id": 601,
   "lat": 60.147974,
   "lng": 24.754344,
   "name": "Nokkala",
   "total": 1115,
   "origin": 547,
   "originPercent": 0.49058296,
   "destination": 568,
   "destinationPercent": 0.50941704
 },
 {
   "id": 603,
   "lat": 60.151041,
   "lng": 24.754196,
   "name": "Matinlahdenranta",
   "total": 1259,
   "origin": 611,
   "originPercent": 0.485305798,
   "destination": 648,
   "destinationPercent": 0.514694202
 },
 {
   "id": 607,
   "lat": 60.147921,
   "lng": 24.741546,
   "name": "Nuottaniementie",
   "total": 775,
   "origin": 356,
   "originPercent": 0.459354839,
   "destination": 419,
   "destinationPercent": 0.540645161
 },
 {
   "id": 609,
   "lat": 60.152343,
   "lng": 24.741234,
   "name": "Sepetlahdentie",
   "total": 1302,
   "origin": 640,
   "originPercent": 0.491551459,
   "destination": 662,
   "destinationPercent": 0.508448541
 },
 {
   "id": 611,
   "lat": 60.156258,
   "lng": 24.752489,
   "name": "Matinkartanontie",
   "total": 2918,
   "origin": 1447,
   "originPercent": 0.495887594,
   "destination": 1471,
   "destinationPercent": 0.504112406
 },
 {
   "id": 613,
   "lat": 60.155689,
   "lng": 24.744978,
   "name": "Matinkyläntie",
   "total": 1634,
   "origin": 816,
   "originPercent": 0.499388005,
   "destination": 818,
   "destinationPercent": 0.500611995
 },
 {
   "id": 615,
   "lat": 60.156755,
   "lng": 24.737664,
   "name": "Tiistiläntie",
   "total": 940,
   "origin": 484,
   "originPercent": 0.514893617,
   "destination": 456,
   "destinationPercent": 0.485106383
 },
 {
   "id": 617,
   "lat": 60.153737,
   "lng": 24.729112,
   "name": "Tiistinkallio",
   "total": 925,
   "origin": 430,
   "originPercent": 0.464864865,
   "destination": 495,
   "destinationPercent": 0.535135135
 },
 {
   "id": 619,
   "lat": 60.160645,
   "lng": 24.724835,
   "name": "Etuniementie",
   "total": 646,
   "origin": 333,
   "originPercent": 0.515479876,
   "destination": 313,
   "destinationPercent": 0.484520124
 },
 {
   "id": 621,
   "lat": 60.161138,
   "lng": 24.756272,
   "name": "Hauenkalliontie",
   "total": 1605,
   "origin": 767,
   "originPercent": 0.47788162,
   "destination": 838,
   "destinationPercent": 0.52211838
 },
 {
   "id": 623,
   "lat": 60.161588,
   "lng": 24.74663,
   "name": "Nelikkotie",
   "total": 1330,
   "origin": 683,
   "originPercent": 0.513533835,
   "destination": 647,
   "destinationPercent": 0.486466165
 },
 {
   "id": 625,
   "lat": 60.160015,
   "lng": 24.741294,
   "name": "Suomenlahdentie",
   "total": 8455,
   "origin": 4208,
   "originPercent": 0.497693672,
   "destination": 4247,
   "destinationPercent": 0.502306328
 },
 {
   "id": 627,
   "lat": 60.162403,
   "lng": 24.738416,
   "name": "Piispansilta",
   "total": 5480,
   "origin": 2770,
   "originPercent": 0.505474453,
   "destination": 2710,
   "destinationPercent": 0.494525547
 },
 {
   "id": 629,
   "lat": 60.165603,
   "lng": 24.732688,
   "name": "Piispanportti",
   "total": 1633,
   "origin": 819,
   "originPercent": 0.501530925,
   "destination": 814,
   "destinationPercent": 0.498469075
 },
 {
   "id": 631,
   "lat": 60.162842,
   "lng": 24.721367,
   "name": "Friisilänaukio",
   "total": 865,
   "origin": 416,
   "originPercent": 0.480924855,
   "destination": 449,
   "destinationPercent": 0.519075145
 },
 {
   "id": 633,
   "lat": 60.168971,
   "lng": 24.724908,
   "name": "Avaruuskatu",
   "total": 934,
   "origin": 446,
   "originPercent": 0.47751606,
   "destination": 488,
   "destinationPercent": 0.52248394
 },
 {
   "id": 635,
   "lat": 60.172673,
   "lng": 24.726025,
   "name": "Kuunkatu",
   "total": 1461,
   "origin": 747,
   "originPercent": 0.511293634,
   "destination": 714,
   "destinationPercent": 0.488706366
 },
 {
   "id": 637,
   "lat": 60.174524,
   "lng": 24.729314,
   "name": "Ruomelantie",
   "total": 759,
   "origin": 412,
   "originPercent": 0.542819499,
   "destination": 347,
   "destinationPercent": 0.457180501
 },
 {
   "id": 639,
   "lat": 60.174914,
   "lng": 24.738122,
   "name": "Itäportti",
   "total": 699,
   "origin": 364,
   "originPercent": 0.52074392,
   "destination": 335,
   "destinationPercent": 0.47925608
 },
 {
   "id": 641,
   "lat": 60.167216,
   "lng": 24.735969,
   "name": "Komeetankatu",
   "total": 1480,
   "origin": 794,
   "originPercent": 0.536486486,
   "destination": 686,
   "destinationPercent": 0.463513514
 },
 {
   "id": 643,
   "lat": 60.171548,
   "lng": 24.731472,
   "name": "Auringonkatu",
   "total": 1014,
   "origin": 528,
   "originPercent": 0.520710059,
   "destination": 486,
   "destinationPercent": 0.479289941
 },
 {
   "id": 645,
   "lat": 60.168441,
   "lng": 24.743532,
   "name": "Piispankallio",
   "total": 959,
   "origin": 491,
   "originPercent": 0.511991658,
   "destination": 468,
   "destinationPercent": 0.488008342
 },
 {
   "id": 647,
   "lat": 60.172814,
   "lng": 24.745666,
   "name": "Lystimäki",
   "total": 726,
   "origin": 349,
   "originPercent": 0.480716253,
   "destination": 377,
   "destinationPercent": 0.519283747
 },
 {
   "id": 649,
   "lat": 60.17471,
   "lng": 24.752442,
   "name": "Lystimäensilta",
   "total": 728,
   "origin": 370,
   "originPercent": 0.508241758,
   "destination": 358,
   "destinationPercent": 0.491758242
 },
 {
   "id": 651,
   "lat": 60.184596,
   "lng": 24.744131,
   "name": "Suurpellonaukio",
   "total": 699,
   "origin": 300,
   "originPercent": 0.429184549,
   "destination": 399,
   "destinationPercent": 0.570815451
 },
 {
   "id": 653,
   "lat": 60.187052,
   "lng": 24.742571,
   "name": "Lukutori",
   "total": 471,
   "origin": 216,
   "originPercent": 0.458598726,
   "destination": 255,
   "destinationPercent": 0.541401274
 },
 {
   "id": 701,
   "lat": 60.206142,
   "lng": 24.840699,
   "name": "Gallen-Kallelan tie",
   "total": 1161,
   "origin": 591,
   "originPercent": 0.509043928,
   "destination": 570,
   "destinationPercent": 0.490956072
 },
 {
   "id": 703,
   "lat": 60.203852,
   "lng": 24.8231,
   "name": "Elfvik",
   "total": 313,
   "origin": 154,
   "originPercent": 0.49201278,
   "destination": 159,
   "destinationPercent": 0.50798722
 },
 {
   "id": 705,
   "lat": 60.203892,
   "lng": 24.80493,
   "name": "Laajalahden keskus",
   "total": 761,
   "origin": 384,
   "originPercent": 0.504599212,
   "destination": 377,
   "destinationPercent": 0.495400788
 },
 {
   "id": 707,
   "lat": 60.210735,
   "lng": 24.824954,
   "name": "Majurinkulma",
   "total": 2598,
   "origin": 1296,
   "originPercent": 0.498845266,
   "destination": 1302,
   "destinationPercent": 0.501154734
 },
 {
   "id": 709,
   "lat": 60.212508,
   "lng": 24.819549,
   "name": "Yhdyskunnankuja",
   "total": 1511,
   "origin": 751,
   "originPercent": 0.49702184,
   "destination": 760,
   "destinationPercent": 0.50297816
 },
 {
   "id": 711,
   "lat": 60.215751,
   "lng": 24.826368,
   "name": "Kirjurinkuja",
   "total": 3807,
   "origin": 1806,
   "originPercent": 0.474389283,
   "destination": 2001,
   "destinationPercent": 0.525610717
 },
 {
   "id": 713,
   "lat": 60.216067,
   "lng": 24.819396,
   "name": "Upseerinkatu",
   "total": 1277,
   "origin": 636,
   "originPercent": 0.498042287,
   "destination": 641,
   "destinationPercent": 0.501957713
 },
 {
   "id": 715,
   "lat": 60.216222,
   "lng": 24.821932,
   "name": "Komentajankatu",
   "total": 1711,
   "origin": 845,
   "originPercent": 0.493863238,
   "destination": 866,
   "destinationPercent": 0.506136762
 },
 {
   "id": 719,
   "lat": 60.213443,
   "lng": 24.811572,
   "name": "Säteri",
   "total": 1491,
   "origin": 744,
   "originPercent": 0.498993964,
   "destination": 747,
   "destinationPercent": 0.501006036
 },
 {
   "id": 721,
   "lat": 60.214193,
   "lng": 24.805613,
   "name": "Säterinrinne",
   "total": 687,
   "origin": 353,
   "originPercent": 0.513828239,
   "destination": 334,
   "destinationPercent": 0.486171761
 },
 {
   "id": 723,
   "lat": 60.214666,
   "lng": 24.800486,
   "name": "Säterinniitty",
   "total": 903,
   "origin": 435,
   "originPercent": 0.481727575,
   "destination": 468,
   "destinationPercent": 0.518272425
 },
 {
   "id": 725,
   "lat": 60.217261,
   "lng": 24.806279,
   "name": "Rummunlyöjänkatu",
   "total": 1122,
   "origin": 562,
   "originPercent": 0.500891266,
   "destination": 560,
   "destinationPercent": 0.499108734
 },
 {
   "id": 727,
   "lat": 60.217311,
   "lng": 24.812419,
   "name": "Ratsutori",
   "total": 3520,
   "origin": 1772,
   "originPercent": 0.503409091,
   "destination": 1748,
   "destinationPercent": 0.496590909
 },
 {
   "id": 729,
   "lat": 60.218869,
   "lng": 24.813885,
   "name": "Leppävaaranaukio",
   "total": 7159,
   "origin": 3556,
   "originPercent": 0.496717419,
   "destination": 3603,
   "destinationPercent": 0.503282581
 },
 {
   "id": 731,
   "lat": 60.220254,
   "lng": 24.813437,
   "name": "Leppävaarankäytävä",
   "total": 4804,
   "origin": 2405,
   "originPercent": 0.50062448,
   "destination": 2399,
   "destinationPercent": 0.49937552
 },
 {
   "id": 733,
   "lat": 60.221019,
   "lng": 24.813109,
   "name": "Läkkitori",
   "total": 1858,
   "origin": 894,
   "originPercent": 0.48116254,
   "destination": 964,
   "destinationPercent": 0.51883746
 },
 {
   "id": 735,
   "lat": 60.222183,
   "lng": 24.816382,
   "name": "Mestarinkatu",
   "total": 432,
   "origin": 227,
   "originPercent": 0.525462963,
   "destination": 205,
   "destinationPercent": 0.474537037
 },
 {
   "id": 737,
   "lat": 60.223769,
   "lng": 24.812271,
   "name": "Muurarinkuja",
   "total": 1660,
   "origin": 828,
   "originPercent": 0.498795181,
   "destination": 832,
   "destinationPercent": 0.501204819
 },
 {
   "id": 739,
   "lat": 60.223827,
   "lng": 24.826396,
   "name": "Postipuun koulu",
   "total": 581,
   "origin": 294,
   "originPercent": 0.506024096,
   "destination": 287,
   "destinationPercent": 0.493975904
 },
 {
   "id": 741,
   "lat": 60.222154,
   "lng": 24.804898,
   "name": "Gransinmäki",
   "total": 396,
   "origin": 201,
   "originPercent": 0.507575758,
   "destination": 195,
   "destinationPercent": 0.492424242
 },
 {
   "id": 745,
   "lat": 60.224943,
   "lng": 24.800971,
   "name": "Leppävaaran urheilupuisto",
   "total": 1060,
   "origin": 520,
   "originPercent": 0.490566038,
   "destination": 540,
   "destinationPercent": 0.509433962
 },
 {
   "id": 747,
   "lat": 60.226379,
   "lng": 24.804735,
   "name": "Leppävaaran uimahalli",
   "total": 1439,
   "origin": 716,
   "originPercent": 0.497567755,
   "destination": 723,
   "destinationPercent": 0.502432245
 },
 {
   "id": 749,
   "lat": 60.228463,
   "lng": 24.813871,
   "name": "Vallikatu",
   "total": 800,
   "origin": 455,
   "originPercent": 0.56875,
   "destination": 345,
   "destinationPercent": 0.43125
 },
 {
   "id": 751,
   "lat": 60.227827,
   "lng": 24.819614,
   "name": "Vallipolku",
   "total": 632,
   "origin": 354,
   "originPercent": 0.560126582,
   "destination": 278,
   "destinationPercent": 0.439873418
 },
 {
   "id": 753,
   "lat": 60.234401,
   "lng": 24.813954,
   "name": "Linnuntie",
   "total": 1068,
   "origin": 535,
   "originPercent": 0.50093633,
   "destination": 533,
   "destinationPercent": 0.49906367
 },
 {
   "id": 755,
   "lat": 60.230453,
   "lng": 24.824561,
   "name": "Kutsuntatie",
   "total": 527,
   "origin": 259,
   "originPercent": 0.491461101,
   "destination": 268,
   "destinationPercent": 0.508538899
 },
 {
   "id": 757,
   "lat": 60.235089,
   "lng": 24.831397,
   "name": "Painiitty",
   "total": 1017,
   "origin": 488,
   "originPercent": 0.479842675,
   "destination": 529,
   "destinationPercent": 0.520157325
 },
 {
   "id": 761,
   "lat": 60.220467,
   "lng": 24.83939,
   "name": "Mäkkylän asema",
   "total": 511,
   "origin": 258,
   "originPercent": 0.504892368,
   "destination": 253,
   "destinationPercent": 0.495107632
 },
 {
   "id": 763,
   "lat": 60.220551,
   "lng": 24.833536,
   "name": "Kalkkipellonmäki",
   "total": 814,
   "origin": 422,
   "originPercent": 0.518427518,
   "destination": 392,
   "destinationPercent": 0.481572482
 },
 {
   "id": 767,
   "lat": 60.223377,
   "lng": 24.820635,
   "name": "Ruutikatu",
   "total": 481,
   "origin": 268,
   "originPercent": 0.557172557,
   "destination": 213,
   "destinationPercent": 0.442827443
 },
 {
   "id": 769,
   "lat": 60.204582,
   "lng": 24.814794,
   "name": "Tiurintie",
   "total": 531,
   "origin": 270,
   "originPercent": 0.508474576,
   "destination": 261,
   "destinationPercent": 0.491525424
 }
]